aind_behavior_curriculum/__init__.py
aind_behavior_curriculum/base.py
aind_behavior_curriculum/curriculum.py
aind_behavior_curriculum/curriculum_utils.py
aind_behavior_curriculum/py.typed
aind_behavior_curriculum/task.py
aind_behavior_curriculum/trainer.py
aind_behavior_curriculum-0.0.37.dist-info/licenses/LICENSE
example_project/__init__.py
example_project/curriculum.py
example_project/task.py
example_project/trainer.py
example_project/assets/curriculum.json
example_project/assets/curriculum.svg
example_project/assets/curriculum_schema.json
example_project_2/__init__.py
example_project_2/curriculum.py
example_project_2/trainer.py
example_project_2/assets/policy_triangle_curriculum.json
example_project_2/assets/policy_triangle_curriculum.svg
example_project_2/assets/policy_triangle_curriculum_schema.json
example_project_2/assets/stage_triangle_curriculum.json
example_project_2/assets/stage_triangle_curriculum.svg
example_project_2/assets/stage_triangle_curriculum_schema.json
example_project_2/assets/track_curriculum.json
example_project_2/assets/track_curriculum.svg
example_project_2/assets/track_curriculum_schema.json
example_project_2/assets/tree_curriculum.json
example_project_2/assets/tree_curriculum.svg
example_project_2/assets/tree_curriculum_schema.json
aind_behavior_curriculum-0.0.37.dist-info/METADATA
aind_behavior_curriculum-0.0.37.dist-info/WHEEL
aind_behavior_curriculum-0.0.37.dist-info/top_level.txt
aind_behavior_curriculum-0.0.37.dist-info/RECORD
