Metadata-Version: 2.4
Name: aind-behavior-curriculum
Version: 0.0.37
Summary: Generated from aind-library-template
Author-email: Jonathan Wong <jonathan.wong@alleninstitute.org>, Bruno Cruz <bruno.cruz@alleninstitute.org>
License: MIT
Classifier: Programming Language :: Python :: 3
Requires-Python: >=3.11
License-File: LICENSE
Requires-Dist: pydantic>2.7
Requires-Dist: semver>=3.0
Requires-Dist: jinja2>=3.1.3
Provides-Extra: linters
Requires-Dist: ruff; extra == "linters"
Requires-Dist: codespell; extra == "linters"
Requires-Dist: coverage; extra == "linters"
Requires-Dist: interrogate; extra == "linters"
Provides-Extra: dev
Requires-Dist: aind_behavior_curriculum[linters]; extra == "dev"
Provides-Extra: docs
Requires-Dist: Sphinx; extra == "docs"
Requires-Dist: furo; extra == "docs"
Requires-Dist: sphinx-jinja; extra == "docs"
Requires-Dist: sphinx_mdinclude; extra == "docs"
Dynamic: license-file
